setup.py
xickle.py
xickle.egg-info/PKG-INFO
xickle.egg-info/SOURCES.txt
xickle.egg-info/dependency_links.txt
xickle.egg-info/requires.txt
xickle.egg-info/top_level.txt