Metadata-Version: 1.0
Name: xickle
Version: 1.0
Summary: XML-persistence, in the most python-ic way
Home-page: UNKNOWN
Author: Hasan Diwan
Author-email: hasan.diwan@gmail.com
License: PSF
Platform: UNKNOWN
